njactb.py
njactb-0.0.2.dist-info/LICENSE
njactb-0.0.2.dist-info/METADATA
njactb-0.0.2.dist-info/WHEEL
njactb-0.0.2.dist-info/top_level.txt
njactb-0.0.2.dist-info/RECORD
