Metadata-Version: 2.1
Name: njactb
Version: 0.0.2
Summary: Python wrapper for njactb.
Home-page: https://github.com/AlJohri/njactb
Author: Al Johri
Author-email: al.johri@gmail.com
License: MIT
Platform: UNKNOWN
Classifier: Programming Language :: Python :: 3 :: Only
Classifier: Programming Language :: Python :: 3.6
Classifier: Programming Language :: Python :: 3.7
Classifier: Programming Language :: Python :: 3.8
Classifier: License :: OSI Approved :: MIT License
Requires-Dist: requests
Requires-Dist: cssselect
Requires-Dist: lxml
Requires-Dist: usaddress
